garlicconfig/__init__.py
garlicconfig/encoding.cpp
garlicconfig/encoding.cpython-39-aarch64-linux-gnu.so
garlicconfig/error_handling_utility.cpp
garlicconfig/exceptions.cpp
garlicconfig/exceptions.cpython-39-aarch64-linux-gnu.so
garlicconfig/fields.cpp
garlicconfig/fields.cpython-39-aarch64-linux-gnu.so
garlicconfig/layer.cpp
garlicconfig/layer.cpython-39-aarch64-linux-gnu.so
garlicconfig/managers.py
garlicconfig/models.py
garlicconfig/repositories.cpp
garlicconfig/repositories.cpython-39-aarch64-linux-gnu.so
garlicconfig/utility.cpp
garlicconfig/utils.py
garlicconfig.libs/libGarlicConfig-0b097c87.so.1.0.1
garlicconfig.libs/libgcc_s-2d945d6c.so.1
garlicconfig.libs/libstdc++-85f2cd6d.so.6.0.33
garlicconfig-1.4.1.dist-info/METADATA
garlicconfig-1.4.1.dist-info/WHEEL
garlicconfig-1.4.1.dist-info/top_level.txt
garlicconfig-1.4.1.dist-info/RECORD
garlicconfig-1.4.1.dist-info/licenses/LICENSE
