Metadata-Version: 2.4
Name: garlicconfig
Version: 1.4.1
Summary: InfoScout GarlicConfig
Home-page: https://github.com/infoscout/garlicconfig
Download-URL: https://github.com/infoscout/garlicconfig/archive/1.4.1.tar.gz
Author: Peyman Mortazavi
Author-email: pey.mortazavi@gmail.com
Keywords: configs,settings
License-File: LICENSE
Dynamic: author
Dynamic: author-email
Dynamic: description
Dynamic: description-content-type
Dynamic: download-url
Dynamic: home-page
Dynamic: keywords
Dynamic: license-file
Dynamic: summary
